obsidian_traverse.py
obsidian_traverse-0.0.1.dist-info/METADATA
obsidian_traverse-0.0.1.dist-info/WHEEL
obsidian_traverse-0.0.1.dist-info/entry_points.txt
obsidian_traverse-0.0.1.dist-info/top_level.txt
obsidian_traverse-0.0.1.dist-info/RECORD
