Metadata-Version: 2.1
Name: obsidian-traverse
Version: 0.0.1
Summary: Recursively list all files linked by Obsidian note.
Home-page: https://github.com/Layerex/obsidian-traverse
Author: Layerex
Author-email: layerex@dismail.de
Classifier: Development Status :: 6 - Mature
Classifier: Programming Language :: Python :: 3
Classifier: License :: OSI Approved :: GNU General Public License v3 (GPLv3)
Classifier: Operating System :: OS Independent
Classifier: Topic :: Utilities
